py_proc_watch.py
py_proc_watch-0.2.4.dist-info/entry_points.txt
py_proc_watch-0.2.4.dist-info/LICENSE.md
py_proc_watch-0.2.4.dist-info/METADATA
py_proc_watch-0.2.4.dist-info/WHEEL
py_proc_watch-0.2.4.dist-info/RECORD
