Metadata-Version: 2.3
Name: py-proc-watch
Version: 0.2.4
Summary: Pure Python procps "watch" replacement
License: MIT
Author: Krzysztof Pawlik
Author-email: krzysiek.pawlik@people.pl
Maintainer: Krzysztof Pawlik
Maintainer-email: krzysiek.pawlik@people.pl
Requires-Python: >=3.9,<4.0
Classifier: Development Status :: 4 - Beta
Classifier: Environment :: Console
Classifier: Intended Audience :: Developers
Classifier: Intended Audience :: End Users/Desktop
Classifier: Intended Audience :: System Administrators
Classifier: License :: OSI Approved :: MIT License
Classifier: Operating System :: OS Independent
Classifier: Programming Language :: Python :: 3
Classifier: Programming Language :: Python :: 3.9
Classifier: Programming Language :: Python :: 3.10
Classifier: Programming Language :: Python :: 3.11
Classifier: Programming Language :: Python :: 3.12
Classifier: Programming Language :: Python :: 3.13
Classifier: Topic :: System :: Monitoring
Classifier: Topic :: Utilities
Requires-Dist: colorama (>=0.4.0,<0.5.0)
Project-URL: Homepage, https://gitlab.com/nelchael/py-proc-watch
Project-URL: Repository, https://gitlab.com/nelchael/py-proc-watch
